{
  "degrade_streak": 0,
  "stable_hash": "0fc8bd2a0d9b8aad",
  "stable_overrides": {
    "AUTO_TRADE_TOP_N": "80",
    "MAX_TOKEN_COOLDOWN_SECONDS": "0",
    "MIN_EXPECTED_EDGE_PERCENT": "0.05",
    "MIN_EXPECTED_EDGE_USD": "0.0005",
    "PAPER_TRADE_SIZE_MIN_USD": "0.1",
    "PAPER_TRADE_SIZE_MAX_USD": "2.5",
    "PAPER_WATCHLIST_MIN_SCORE": "70",
    "PAPER_WATCHLIST_MIN_VOLUME_5M_USD": "10",
    "SAFE_MIN_VOLUME_5M_USD": "5",
    "V2_SOURCE_QOS_TOPK_PER_CYCLE": "600",
    "V2_SOURCE_QOS_MAX_PER_SYMBOL_PER_CYCLE": "1",
    "V2_SOURCE_QOS_SOURCE_CAPS": "onchain:352,onchain+market:348,dexscreener:320,geckoterminal:315,watchlist:16,dex_boosts:140",
    "V2_UNIVERSE_NOVELTY_MIN_SHARE": "0.85",
    "SYMBOL_CONCENTRATION_MAX_SHARE": "0.12",
    "V2_UNIVERSE_SOURCE_CAPS": "onchain:224,onchain+market:223,dexscreener:201,geckoterminal:197,watchlist:4,dex_boosts:128",
    "PLAN_MAX_SINGLE_SOURCE_SHARE": "0.2",
    "PLAN_MAX_WATCHLIST_SHARE": "0.14",
    "PLAN_MIN_NON_WATCHLIST_PER_BATCH": "2",
    "PROFIT_ENGINE_ENABLED": "false",
    "MARKET_MODE_STRICT_SCORE": "35",
    "MARKET_MODE_SOFT_SCORE": "30",
    "V2_QUALITY_SYMBOL_MAX_SHARE": "0.24",
    "V2_QUALITY_SYMBOL_MIN_ABS_CAP": "6",
    "V2_QUALITY_SYMBOL_REENTRY_MIN_SECONDS": "60",
    "MIN_TRADE_USD": "0.10",
    "EV_FIRST_ENTRY_MIN_NET_USD": "-0.002",
    "EV_FIRST_ENTRY_CORE_PROBE_EV_TOLERANCE_USD": "0.01",
    "SOURCE_ROUTER_MIN_TRADES": "14",
    "SOURCE_ROUTER_BAD_ENTRY_PROBABILITY": "0.95",
    "SOURCE_ROUTER_SEVERE_ENTRY_PROBABILITY": "0.9",
    "HEAVY_CHECK_DEDUP_TTL_SECONDS": "0",
    "TOKEN_EV_MEMORY_SEVERE_ENTRY_PROBABILITY": "0.9",
    "TOKEN_EV_MEMORY_MIN_TRADES": "18",
    "TOKEN_EV_MEMORY_BAD_ENTRY_PROBABILITY": "0.95",
    "V2_QUALITY_SOURCE_BUDGET_ENABLED": "false",
    "V2_ROLLING_EDGE_MIN_USD": "0.0005",
    "V2_CALIBRATION_ENABLED": "true",
    "V2_CALIBRATION_EDGE_USD_MIN": "0.003",
    "V2_CALIBRATION_VOLUME_MIN": "5",
    "V2_ROLLING_EDGE_MIN_PERCENT": "0.05",
    "PAPER_WATCHLIST_MIN_LIQUIDITY_USD": "10000",
    "SEEN_TOKEN_TTL": "1800",
    "TOKEN_AGE_MAX": "21600",
    "WATCHLIST_MAX_TOKENS": "120",
    "WATCHLIST_MIN_LIQUIDITY_USD": "5000",
    "WATCHLIST_MIN_VOLUME_24H_USD": "10000",
    "WATCHLIST_REFRESH_SECONDS": "960"
  },
  "last_phase": "expand",
  "last_effective_hash": "648525a0c1a75697",
  "last_effective_at": "2026-02-28T12:33:07.025096+00:00",
  "churn_lock_symbol": "",
  "churn_lock_until_ts": 0.0,
  "churn_lock_last_reason": "ttl_expired",
  "effective_target_trades_per_hour": 4.0,
  "effective_target_stable_ticks": 0,
  "effective_target_fail_ticks": 1,
  "effective_target_last_reason": "hold observed=8.00 headroom=12.00 stable=0 fail=1",
  "updated_at": "2026-02-28T13:49:46.661387+00:00"
}
